molgeom/__init__.py
molgeom/atom.py
molgeom/molecule.py
molgeom/cli/cli_main.py
molgeom/data/bond_lengths.json
molgeom/data/bond_lengths.yaml
molgeom/data/bond_pairs_len.json
molgeom/data/bonds_jmol_ob.json
molgeom/data/bonds_jmol_ob.yaml
molgeom/data/consts.py
molgeom/data/implicit_valence.py
molgeom/data/periodic_table.json
molgeom/data/periodic_table.yaml
molgeom/parsers/__init__.py
molgeom/parsers/cif.py
molgeom/parsers/gamess.py
molgeom/parsers/gaussian.py
molgeom/parsers/mol.py
molgeom/parsers/parser_selector.py
molgeom/parsers/parser_tools.py
molgeom/parsers/poscar.py
molgeom/parsers/sdf.py
molgeom/parsers/xyz.py
molgeom/templates/mol_view_template.html
molgeom/utils/__init__.py
molgeom/utils/decorators.py
molgeom/utils/fancy_indexing_list.py
molgeom/utils/html_utils.py
molgeom/utils/lattice_utils.py
molgeom/utils/mat3.py
molgeom/utils/symmetry_utils.py
molgeom/utils/vec3.py
molgeom-0.8.0.dist-info/METADATA
molgeom-0.8.0.dist-info/WHEEL
molgeom-0.8.0.dist-info/entry_points.txt
molgeom-0.8.0.dist-info/licenses/LICENSE
molgeom-0.8.0.dist-info/RECORD
