Metadata-Version: 2.4
Name: molgeom
Version: 0.8.0
Summary: A simple molecular geometry manipulation library.
Project-URL: Homepage, https://github.com/sio-salt/molgeom
Project-URL: Repository, https://github.com/sio-salt/molgeom
Project-URL: Documentation, https://github.com/sio-salt/molgeom-examples
Author-email: sio-salt <saltinthedesertyou@gmail.com>
License: MIT License
License-File: LICENSE
Keywords: CIF,GAMESS,VASP,analysis,chemistry,computation,crystal,gaussian,geometry,molecular,qchem,quantum,science,structure,xyz
Classifier: Development Status :: 5 - Production/Stable
Classifier: Intended Audience :: Science/Research
Classifier: License :: OSI Approved :: MIT License
Classifier: Operating System :: OS Independent
Classifier: Programming Language :: Python
Classifier: Programming Language :: Python :: 3
Classifier: Programming Language :: Python :: 3 :: Only
Classifier: Programming Language :: Python :: 3.10
Classifier: Programming Language :: Python :: 3.11
Classifier: Programming Language :: Python :: 3.12
Classifier: Programming Language :: Python :: 3.13
Classifier: Topic :: Scientific/Engineering :: Chemistry
Classifier: Topic :: Scientific/Engineering :: Information Analysis
Classifier: Topic :: Scientific/Engineering :: Physics
Classifier: Topic :: Scientific/Engineering :: Quantum Computing
Classifier: Topic :: Scientific/Engineering :: Visualization
Classifier: Topic :: Software Development :: Libraries :: Python Modules
Requires-Python: >=3.10
Requires-Dist: cachetools>=5.2.0
Requires-Dist: click>=8.1.7
Requires-Dist: networkx>=2.6.3
